cchem_input_formatter/__init__.py
cchem_input_formatter/formatters.py
cchem_input_formatter-0.0.4.dist-info/LICENSE
cchem_input_formatter-0.0.4.dist-info/METADATA
cchem_input_formatter-0.0.4.dist-info/WHEEL
cchem_input_formatter-0.0.4.dist-info/top_level.txt
cchem_input_formatter-0.0.4.dist-info/RECORD
