Metadata-Version: 2.1
Name: cchem_input_formatter
Version: 0.0.4
Summary: comp chem input formatters
Author: Ben Payton
Author-email: bennyp2494@gmail.com
Keywords: python,compchem
Classifier: Development Status :: 1 - Planning
Classifier: Intended Audience :: Developers
Classifier: Programming Language :: Python :: 3
Classifier: Operating System :: Unix
Classifier: Operating System :: MacOS :: MacOS X
Classifier: Operating System :: Microsoft :: Windows
License-File: LICENSE
